Metadata-Version: 1.1
Name: mongua
Version: 0.0.2
Summary: Mongua , which encapsulates MongoMixin by pymongo, make use of MongoDB in someway like relative database
Home-page: http://github.com/dodoru/mongua
Author: dodoru
Author-email: dodoru@foxmail.com
License: MIT
Keywords: MongoDB pymongo mongua MongoMixin
Platform: any
Classifier: Development Status :: 3 - Alpha
Classifier: Intended Audience :: Developers
Classifier: Topic :: Software Development :: Build Tools
Classifier: Topic :: Software Development :: Libraries :: Python Modules
Classifier: Topic :: Internet :: WWW/HTTP :: Dynamic Content
Classifier: License :: OSI Approved :: MIT License
Classifier: Programming Language :: Python :: 3.4
Classifier: Programming Language :: Python :: 3.5
Classifier: Programming Language :: Python :: 3.6
